<XMBML version="1.0">
	<View id="updategames_items">
		<Attributes>
		 <Table key="updategames_items">
			<Pair key="icon"><String>/dev_hdd0/game/TCXSPROJECT/USRDIR/IMAGES/DLCS/download.png</String></Pair>
			<Pair key="title"><String>TCXS - Elefunk™ UPDATE</String></Pair>
			<Pair key="info"><String>TCXS -  Game id: id:UP9000-NPUA80157 </String></Pair>
			<Pair key="module_name"><String>webrender_plugin</String></Pair>
			<Pair key="module_action"><String>http://b0.ww.np.dl.playstation.net/tppkg/np/NPUA80157/NPUA80157_T0/a9b50fbfe951e6d3/UP9000-NPUA80157_00-ELEFUNKPATCH0110-A0110-V0100-PE.pkg</String></Pair>
         </Table>
		</Attributes>
		<Items>
		  <Item class="type:x-xmb/module-action" key="updategames_items" attr="updategames_items"/>
		</Items>
	</View>
</XMBML>